pycanpcap/__init__.py
pycanpcap/log.py
pycanpcap-0.2.dist-info/LICENSE
pycanpcap-0.2.dist-info/METADATA
pycanpcap-0.2.dist-info/WHEEL
pycanpcap-0.2.dist-info/top_level.txt
pycanpcap-0.2.dist-info/RECORD
