Metadata-Version: 2.1
Name: pycanpcap
Version: 0.2
Summary: candump and write a pcap using scapy (and python-can)
Home-page: https://github.com/BenGardiner/pycanpcap
Author: Ben Gardiner
Author-email: ben.l.gardiner@gmail.com
Classifier: License :: OSI Approved :: MIT License
Classifier: Programming Language :: Python
Classifier: Programming Language :: Python :: 3.9
License-File: LICENSE
Requires-Dist: scapy >=2.4.5
Requires-Dist: python-can ~=4.3.1
